naver_sens/__init__.py
naver_sens/naver_sens.py
naver_sens-0.0.1.dist-info/LICENSE
naver_sens-0.0.1.dist-info/METADATA
naver_sens-0.0.1.dist-info/WHEEL
naver_sens-0.0.1.dist-info/top_level.txt
naver_sens-0.0.1.dist-info/RECORD
